{
  "estados": [
    {
      "color": null,
      "icono": null,
      "nombre": "Nuevo",
      "orden": 1,
      "es_inicial": true,
      "empresa_id": null
    },
    {
      "color": "#7c3aed",
      "icono": null,
      "nombre": "Prospecto",
      "orden": 2,
      "es_inicial": false,
      "empresa_id": null
    },
    {
      "color": "#54ed40",
      "icono": null,
      "nombre": "Activo",
      "orden": 3,
      "es_inicial": false,
      "empresa_id": null
    },
    {
      "color": "#ed4040",
      "icono": null,
      "nombre": "Baja",
      "orden": 4,
      "es_inicial": false,
      "empresa_id": null
    }
  ],
  "transiciones": [
    {
      "etiqueta": "Activar",
      "accion": "activar",
      "reglas": [],
      "empresa_id": null,
      "campos_editables": [
        "pty_clientes_nombre",
        "pty_clientes_edad"
      ],
      "estado_destino": "Activo",
      "estado_origen": "Prospecto"
    },
    {
      "etiqueta": "Calificar como prospecto",
      "accion": "calificar",
      "reglas": [],
      "empresa_id": null,
      "campos_editables": [],
      "estado_destino": "Prospecto",
      "estado_origen": "Nuevo"
    },
    {
      "etiqueta": "Dar de baja",
      "accion": "dar_de_baja",
      "reglas": [],
      "empresa_id": null,
      "campos_editables": [
        "pty_clientes_fecha_baja"
      ],
      "estado_destino": "Baja",
      "estado_origen": "Activo"
    },
    {
      "etiqueta": "Guardar",
      "accion": "guardar",
      "reglas": [],
      "empresa_id": null,
      "campos_editables": [
        "pty_clientes_nombre",
        "pty_clientes_edad",
        "pty_clientes_venta"
      ],
      "estado_destino": "Activo",
      "estado_origen": "Activo"
    },
    {
      "etiqueta": "Reactivar",
      "accion": "reactivar",
      "reglas": [],
      "empresa_id": null,
      "campos_editables": [],
      "estado_destino": "Activo",
      "estado_origen": "Baja"
    }
  ],
  "catalogo": "pty_clientes"
}